agent_control_hub-1.0.0.dist-info/licenses/LICENSE
agents/__init__.py
agents/factory.py
core/__init__.py
core/config.py
models/__init__.py
models/responses.py
routers/__init__.py
routers/projects.py
services/__init__.py
services/pipeline.py
services/plan.py
src/__init__.py
src/main.py
src/llm/__init__.py
src/llm/llm_provider.py
src/ui/__init__.py
src/ui/streamlit/__init__.py
src/ui/streamlit/streamlit_app.py
tests/__init__.py
tests/test_basic.py
tests/test_llm_provider.py
tests/test_utils.py
agent_control_hub-1.0.0.dist-info/METADATA
agent_control_hub-1.0.0.dist-info/WHEEL
agent_control_hub-1.0.0.dist-info/entry_points.txt
agent_control_hub-1.0.0.dist-info/top_level.txt
agent_control_hub-1.0.0.dist-info/RECORD
