Metadata-Version: 2.4
Name: agent-control-hub
Version: 1.0.0
Summary: A centralized hub for multi-agent code creation, enhancement, and deployment
Home-page: https://github.com/Dzg0507/AgentHub
Author: Agent Control Hub Team
Author-email: contact@agentcontrolhub.dev
Maintainer: Dzg0507
Maintainer-email: contact@agentcontrolhub.dev
License: MIT
Project-URL: Homepage, https://github.com/Dzg0507/AgentHub
Project-URL: Documentation, https://github.com/Dzg0507/AgentHub#readme
Project-URL: Repository, https://github.com/Dzg0507/AgentHub.git
Project-URL: Bug Tracker, https://github.com/Dzg0507/AgentHub/issues
Project-URL: Changelog, https://github.com/Dzg0507/AgentHub/blob/main/CHANGELOG.md
Project-URL: Contributing, https://github.com/Dzg0507/AgentHub/blob/main/CONTRIBUTING.md
Keywords: ai,artificial-intelligence,code-generation,multi-agent,streamlit,fastapi,llm,machine-learning,automation,development-tools,code-assistant,agent-framework
Platform: any
Classifier: Development Status :: 5 - Production/Stable
Classifier: Intended Audience :: Developers
Classifier: Intended Audience :: Science/Research
Classifier: Operating System :: OS Independent
Classifier: Programming Language :: Python :: 3
Classifier: Programming Language :: Python :: 3.8
Classifier: Programming Language :: Python :: 3.9
Classifier: Programming Language :: Python :: 3.10
Classifier: Programming Language :: Python :: 3.11
Classifier: Programming Language :: Python :: 3.12
Classifier: Topic :: Software Development :: Code Generators
Classifier: Topic :: Software Development :: Libraries :: Python Modules
Classifier: Topic :: Scientific/Engineering :: Artificial Intelligence
Classifier: Topic :: Internet :: WWW/HTTP :: Dynamic Content
Classifier: Topic :: Software Development :: User Interfaces
Classifier: Topic :: Software Development :: Libraries :: Application Frameworks
Requires-Python: >=3.8
License-File: LICENSE
Requires-Dist: ag2[gemini]>=0.8
Requires-Dist: fastapi>=0.110
Requires-Dist: uvicorn[standard]>=0.22
Requires-Dist: python-dotenv>=1.0
Requires-Dist: streamlit>=1.37
Requires-Dist: requests>=2.31
Requires-Dist: psutil>=5.9
Requires-Dist: google-generativeai>=0.3.0
Requires-Dist: pytest>=7.0
Requires-Dist: pytest-cov>=4.0
Requires-Dist: flake8>=6.0
Requires-Dist: black>=23.0
Provides-Extra: dev
Requires-Dist: pytest>=7.0.0; extra == "dev"
Requires-Dist: pytest-cov>=4.0.0; extra == "dev"
Requires-Dist: pytest-asyncio>=0.21.0; extra == "dev"
Requires-Dist: flake8>=6.0.0; extra == "dev"
Requires-Dist: black>=23.0.0; extra == "dev"
Requires-Dist: mypy>=1.0.0; extra == "dev"
Requires-Dist: bandit>=1.7.0; extra == "dev"
Requires-Dist: safety>=2.0.0; extra == "dev"
Requires-Dist: pre-commit>=3.0.0; extra == "dev"
Provides-Extra: docs
Requires-Dist: mkdocs>=1.4.0; extra == "docs"
Requires-Dist: mkdocs-material>=9.0.0; extra == "docs"
Requires-Dist: mkdocs-mermaid2-plugin>=1.0.0; extra == "docs"
Provides-Extra: all
Requires-Dist: pytest>=7.0.0; extra == "all"
Requires-Dist: pytest-cov>=4.0.0; extra == "all"
Requires-Dist: pytest-asyncio>=0.21.0; extra == "all"
Requires-Dist: flake8>=6.0.0; extra == "all"
Requires-Dist: black>=23.0.0; extra == "all"
Requires-Dist: mypy>=1.0.0; extra == "all"
Requires-Dist: bandit>=1.7.0; extra == "all"
Requires-Dist: safety>=2.0.0; extra == "all"
Requires-Dist: pre-commit>=3.0.0; extra == "all"
Requires-Dist: mkdocs>=1.4.0; extra == "all"
Requires-Dist: mkdocs-material>=9.0.0; extra == "all"
Requires-Dist: mkdocs-mermaid2-plugin>=1.0.0; extra == "all"
Dynamic: author
Dynamic: author-email
Dynamic: classifier
Dynamic: description
Dynamic: description-content-type
Dynamic: home-page
Dynamic: keywords
Dynamic: license
Dynamic: license-file
Dynamic: maintainer
Dynamic: maintainer-email
Dynamic: platform
Dynamic: project-url
Dynamic: provides-extra
Dynamic: requires-dist
Dynamic: requires-python
Dynamic: summary
